citros_meta.py
citros/__init__.py
citros/citros.py
citros/citros_bag.py
citros/citros_batch.py
citros/citros_events.py
citros/citros_integration.py
citros/citros_params.py
citros/citros_utils.py
citros/launches/__init__.py
citros/launches/launch.py
citros/logger/__init__.py
citros/logger/logger.py
citros/logger/logger_pg_handler.py
citros/parsers/__init__.py
citros/parsers/parser_base.py
citros/parsers/parser_ros2.py
citros/rosbag/__init__.py
citros/rosbag/reader_base.py
citros/rosbag/reader_mcap.py
citros/rosbag/reader_sqlite.py
citros-23.25.7.data/scripts/citros
citros-23.25.7.dist-info/LICENSE
citros-23.25.7.dist-info/METADATA
citros-23.25.7.dist-info/WHEEL
citros-23.25.7.dist-info/top_level.txt
citros-23.25.7.dist-info/RECORD
