Metadata-Version: 2.1
Name: citros
Version: 23.25.7
Summary: A cli entrypoint for the citros system.
Home-page: http://pypi.python.org/pypi/citros_cli/
Author: vovacooper
Author-email: vova@lulav.space
License: LICENSE.txt
License-File: LICENSE
Requires-Dist: ansicolors (==1.1.8)
Requires-Dist: gql (==3.4.0)
Requires-Dist: graphql-core (==3.2.3)
Requires-Dist: pymongo (==4.3.3)
Requires-Dist: requests (==2.28.1)
Requires-Dist: rosdep (==0.22.1)
Requires-Dist: python-decouple
Requires-Dist: requests-toolbelt
Requires-Dist: soupsieve
Requires-Dist: bs4
Requires-Dist: zipp
Requires-Dist: pyjwt
Requires-Dist: psycopg2-binary
Requires-Dist: urllib3 (>=1.26)
Requires-Dist: InquirerPy
Requires-Dist: faker
